django_nocaptcha_recaptcha_inv-1.0.2.dist-info/DESCRIPTION.rst
django_nocaptcha_recaptcha_inv-1.0.2.dist-info/METADATA
django_nocaptcha_recaptcha_inv-1.0.2.dist-info/RECORD
django_nocaptcha_recaptcha_inv-1.0.2.dist-info/WHEEL
django_nocaptcha_recaptcha_inv-1.0.2.dist-info/metadata.json
django_nocaptcha_recaptcha_inv-1.0.2.dist-info/top_level.txt
nocaptcha_recaptcha/__init__.py
nocaptcha_recaptcha/_compat.py
nocaptcha_recaptcha/client.py
nocaptcha_recaptcha/fields.py
nocaptcha_recaptcha/models.py
nocaptcha_recaptcha/tests.py
nocaptcha_recaptcha/views.py
nocaptcha_recaptcha/widgets.py
nocaptcha_recaptcha/templates/nocaptcha_recaptcha/widget_invisible.html
nocaptcha_recaptcha/templates/nocaptcha_recaptcha/widget_nocaptcha.html
