Metadata-Version: 2.0
Name: django-nocaptcha-recaptcha-inv
Version: 1.0.2
Summary: https://github.com/ImaginaryLandscape/django-nocaptcha-recaptcha
Home-page: https://github.com/ricardochaves/django-nocaptcha-recaptcha-inv
Author: Ricardo Baltazar Chaves
Author-email: ricardobchaves6@gmail.com
License: BSD
Keywords: django,recaptcha,field
Platform: UNKNOWN
Classifier: Development Status :: 5 - Production/Stable
Classifier: Environment :: Web Environment
Classifier: Framework :: Django
Classifier: Framework :: Django :: 2.0
Classifier: Intended Audience :: Developers
Classifier: License :: OSI Approved :: BSD License
Classifier: Operating System :: OS Independent
Classifier: Programming Language :: Python
Classifier: Programming Language :: Python :: 3
Classifier: Programming Language :: Python :: 3.4
Classifier: Programming Language :: Python :: 3.5
Classifier: Programming Language :: Python :: 3.6
Classifier: Topic :: Internet :: WWW/HTTP
Classifier: Topic :: Internet :: WWW/HTTP :: Dynamic Content
Classifier: Topic :: Internet :: WWW/HTTP :: WSGI
Classifier: Topic :: Software Development :: Libraries :: Application Frameworks
Classifier: Topic :: Software Development :: Libraries :: Python Modules
Classifier: Natural Language :: Portuguese (Brazilian)
